<?xml version="1.0"?>
<layout
	version="142"
	comment=""
	precache_condition="">
	<hierarchy>
		<root this="34001338-B13C-4056-8A97BE79D1094FA9">
			<control_pane this="34002338-B13C-4056-8A97BE79D1094FA9">
                <player_pane this="34003338-B13C-4056-8A97BE79D1094FA9">
                    <player_title this="94CFD847-4974-4957-B0800EB7BA0DD999"/>
                    <player_holder this="34004338-B13C-4056-8A97BE79D1094FA9">
                        <player_crest this="34005338-B13C-4056-8A97BE79D1094FA9"/>
                    </player_holder>
                </player_pane>
                <control_buttons this="E6B61D77-A8CE-4A2A-86350D32CA78886A">
                    <button_hero_phase this="4C655407-1453-4C0C-8D08AB305550B6FC"/>
                    <button_move_phase this="34A720E2-1272-4654-94D8C98F2A71485D"/>
                    <button_shoot_phase this="45A720E2-1272-4654-94D8C98F2A71485D"/>
                    <button_charge_phase this="56A720E2-1272-4654-94D8C98F2A71485D"/>
                    <button_fight_phase this="67A720E2-1272-4654-94D8C98F2A71485D"/>
                </control_buttons>
                <next_phase_button this="78A720E2-1272-4654-94D8C98F2A71485D"/>
            </control_pane>
		</root>
	</hierarchy>
	<components>
        <control_pane 
            this="34002338-B13C-4056-8A97BE79D1094FA9"
            id="control_pane"
            allowverticalresize="false"
			docking="Top Center"
            currentstate="B360758B-FB1F-4ABE-B46206C61628F261"
			defaultstate="B360758B-FB1F-4ABE-B46206C61628F261">
			<userproperties>
				<property
					name="WH2_margin_left"
					value="50"/>
				<property
					name="WH2_margin_right"
					value="80"/>
			</userproperties>
			<componentimages>
				<component_image
					this="FD4F4453-1BEE-4F15-A07A8AF101627C8F"
					uniqueguid="FD4F4453-1BEE-4F15-A07A8AF101627C8F"
					imagepath="ui/skins/default/bar_small_buttons_2.png"/>
			</componentimages>
			<states>
				<newstate
					this="B360758B-FB1F-4ABE-B46206C61628F261"
					name="NewState"
					width="2040"
					height="29"
					pixelcollision="true"
					uniqueguid="B360758B-FB1F-4ABE-B46206C61628F261">
					<imagemetrics>
						<image
							this="4CE95040-1B9D-4A46-B03F63473DA3E15A"
							uniqueguid="4CE95040-1B9D-4A46-B03F63473DA3E15A"
							componentimage="FD4F4453-1BEE-4F15-A07A8AF101627C8F"
							offset="0.00,-14.00"
							width="2040"
							height="67"
							tile="true"
							dockpoint="Top Center"
							dock_offset="0.00,-14.00"
							margin="0.00,150.00,0.00,150.00"/>
					</imagemetrics>
				</newstate>
			</states>
			<LayoutEngine
				type="HorizontalList"
				spacing="10.00,0.00"
				sizetocontent="true"
				margins="150.00,140.00"/>

        </control_pane>
        <player_pane 
            this="34003338-B13C-4056-8A97BE79D1094FA9"
            id="player_pane">
        </player_pane>
        <player_title 
            this="94CFD847-4974-4957-B0800EB7BA0DD999"
            id="player_title"
			offset="0.00,0.00"
			allowverticalresize="false"
			allowhorizontalresize="false"
			docking="Top Center"
			dock_offset="0.00,5.00"
			component_anchor_point="1.00,0.00"
			priority="60"
			tooltipslocalised="true"
			uniqueguid="94CFD847-4974-4957-B0800EB7BA0DD999"
			currentstate="252D0F0F-291B-47AF-897B9DAEC1372135"
			defaultstate="252D0F0F-291B-47AF-897B9DAEC1372135">
			<componentimages>
				<component_image
					this="1526F03A-D2D9-4608-A07620322A1A9E7B"
					uniqueguid="1526F03A-D2D9-4608-A07620322A1A9E7B"
					imagepath="ui/skins/default/panel_title.png"/>
			</componentimages>
			<states>
				<newstate
					this="252D0F0F-291B-47AF-897B9DAEC1372135"
					name="NewState"
					width="650"
					height="59"
					text="The Path"
					textvalign="Center"
					texthalign="Center"
					texthbehaviour="Never split"
					textlocalised="true"
					font_m_font_name="brand_header"
					font_m_size="16"
					font_m_colour="#FFF8D7FF"
					font_m_leading="1"
					fontcat_name="fe_paragraph_heading"
					interactive="true"
					text_shader_name="drop_shadow_t0"
					textshadervars="0.00,1.00,2.00,0.00"
					uniqueguid="252D0F0F-291B-47AF-897B9DAEC1372135">
					<imagemetrics>
						<image
							this="E1A8FA08-66E5-481A-8121F0940C7B3D01"
							uniqueguid="E1A8FA08-66E5-481A-8121F0940C7B3D01"
							componentimage="1526F03A-D2D9-4608-A07620322A1A9E7B"
							offset="0.00,0.00"
							width="650"
							height="59"
							tile="true"
							dockpoint="Center"
							margin="0.00,165.00,0.00,165.00"/>
					</imagemetrics>
				</newstate>
			</states>
        </player_title>
        <player_holder 
            this="34004338-B13C-4056-8A97BE79D1094FA9"
            id="player_holder"
            allowhorizontalresize="false"
			allowverticalresize="false"
			tooltipslocalised="true"
			uniqueguid="2F162AFF-1956-480C-860CC44D3D62BCD2"
			currentstate="1C169801-0D69-4D60-B93307243548C2ED"
			defaultstate="1C169801-0D69-4D60-B93307243548C2ED">
			<states>
				<newstate
					this="1C169801-0D69-4D60-B93307243548C2ED"
					name="NewState"
					width="35"
					height="90"
					uniqueguid="1C169801-0D69-4D60-B93307243548C2ED"/>
			</states>
        </player_holder>
        <player_crest 
            this="34005338-B13C-4056-8A97BE79D1094FA9"
            id="player_crest"
            allowhorizontalresize="false"
			allowverticalresize="false"
			docking="Top Left"
			dock_offset="0.00,0.00"
			priority="1"
			tooltipslocalised="true"
			uniqueguid="71EC1121-925D-45FE-9F495484709B572C"
			currentstate="B2C4F767-E7BE-4C3A-93A3025656CD89E2"
			defaultstate="B2C4F767-E7BE-4C3A-93A3025656CD89E2">
			<componentimages>
				<component_image
					this="DCC92E97-6140-4AB9-92740B95E7087B63"
					uniqueguid="DCC92E97-6140-4AB9-92740B95E7087B63"
					imagepath="ui/skins/default/mon_rotated.png"/>
			</componentimages>
			<states>
				<newstate
					this="B2C4F767-E7BE-4C3A-93A3025656CD89E2"
					name="NewState"
					width="56"
					height="45"
					uniqueguid="B2C4F767-E7BE-4C3A-93A3025656CD89E2">
					<imagemetrics>
						<image
							this="D869125C-064F-4BBF-AE3D034CA434F713"
							uniqueguid="D869125C-064F-4BBF-AE3D034CA434F713"
							componentimage="DCC92E97-6140-4AB9-92740B95E7087B63"
							width="56"
							height="45"
							dockpoint="Center"/>
					</imagemetrics>
				</newstate>
			</states>

        </player_crest>
        <control_buttons 
            this="E6B61D77-A8CE-4A2A-86350D32CA78886A"
            id="control_buttons"
            uniqueguid="E6B61D77-A8CE-4A2A-86350D32CA78886A"
			currentstate="351E044A-FB74-4D38-8F153C9A089F282C">
			<componentimages>
				<component_image
					this="AAD18B9E-E7E0-4CB6-A84BACC1122C21F1"
					uniqueguid="AAD18B9E-E7E0-4CB6-A84BACC1122C21F1"
					imagepath="ui/skins/default/kill_ratio_bar.png"/>
			</componentimages>
			<states>
				<newstate
					this="351E044A-FB74-4D38-8F153C9A089F282C"
					name="NewState"
					width="194"
					height="38"
					interactive="true"
					disabled="true"
					uniqueguid="351E044A-FB74-4D38-8F153C9A089F282C">
					<imagemetrics>
						<image
							this="8623271C-642C-43EF-B36F3E7FA717F323"
							uniqueguid="8623271C-642C-43EF-B36F3E7FA717F323"
							componentimage="AAD18B9E-E7E0-4CB6-A84BACC1122C21F1"
							offset="40.00,11.00"
							width="114"
							height="16"
							colour="#FFFFFF00"
							dockpoint="Center"
							canresizeheight="false"
							canresizewidth="false"
							margin="0.00,4.00,0.00,4.00"/>
					</imagemetrics>
					<component_text
						font_m_colour="#FFF8D7FF"
						font_m_leading="3"
						fontcat_name="body_10"/>
				</newstate>
			</states>
        </control_buttons>
        <button_hero_phase 
            this="4C655407-1453-4C0C-8D08AB305550B6FC"
            id="button_hero_phase"
            template_id="square_button_toggle_40"
			part_of_template="true"
			uniqueguid_in_template="1101BA48-5C83-4D09-9632B78D5B52AC11"
			uniqueguid="4C655407-1453-4C0C-8D08AB305550B6FC"
			dimensions="40.00,40.00"
			dock_point="Center Right"
			offset="-76.00,0.00"
			sound_category="UI_GBL_TMP_Round_Small_Button">
			<state_uniqueguids>
				<state_uniqueguid
					name="active"
					uniqueguid="4E7A65BF-AFB4-4D63-9D5E87145CC41D4D"/>
				<state_uniqueguid
					name="down"
					uniqueguid="AD2D681C-EA7E-4333-A684995201E55B61"/>
				<state_uniqueguid
					name="down_off"
					uniqueguid="430FC846-773B-4CE7-94DC270B2C4DCB86"/>
				<state_uniqueguid
					name="hover"
					uniqueguid="3B1624C7-BDB8-4C27-AFF140AA8EEC8AB9"/>
				<state_uniqueguid
					name="inactive"
					uniqueguid="07BCFC1C-C324-40D7-8E4AF6207E28F435"/>
				<state_uniqueguid
					name="selected"
					uniqueguid="7162627E-99B9-45D3-953AC04A02104662"/>
				<state_uniqueguid
					name="selected_down"
					uniqueguid="7555C34F-A306-49F4-A5F8912D37234966"/>
				<state_uniqueguid
					name="selected_down_off"
					uniqueguid="B9F9EA44-D87F-4099-B1C1DDF6339E0710"/>
				<state_uniqueguid
					name="selected_hover"
					uniqueguid="AF468B97-4E99-4A1B-9E3DEFB338A07AD1"/>
				<state_uniqueguid
					name="selected_inactive"
					uniqueguid="2099706B-4DB1-4AF3-A033E32E08E50119"/>
			</state_uniqueguids>
			<component_image_uniqueguids>
				<component_image_uniqueguid
					name="ui/skins/default/icon_speed_controls_button_play.png"
					uniqueguid="2597AC4C-2CC7-4290-99757027289F716B"/>
				<component_image_uniqueguid
					name="ui/skins/default/button_square_togle_pressed.png"
					uniqueguid="B2B13476-45A8-4BD4-9438CE1A8BD65678"/>
				<component_image_uniqueguid
					name="ui/skins/default/button_square_togle_selected_hover.png"
					uniqueguid="4B179BDF-446C-4865-B8B357BF3F19AF7E"/>
				<component_image_uniqueguid
					name="ui/skins/default/button_square_togle_hover.png"
					uniqueguid="450BF8F5-0377-4B2D-8D130017D751CE45"/>
				<component_image_uniqueguid
					name="ui/skins/default/button_square_togle_active.png"
					uniqueguid="04DF47F5-2311-4007-A02B823D4390A5E2"/>
				<component_image_uniqueguid
					name="ui/skins/default/button_square_togle_inactive.png"
					uniqueguid="2BEA714F-FE22-4418-BCA0E78F250E46CE"/>
				<component_image_uniqueguid
					name="ui/skins/default/button_square_togle_selected.png"
					uniqueguid="35AA89ED-9E9F-4192-9FD9C0ABDABE7596"/>
				<component_image_uniqueguid
					name="ui/skins/default/button_square_togle_underlay.png"
					uniqueguid="0A408CD2-857A-49C4-A55A79FEEDD18AB7"/>
				<component_image_uniqueguid
					name="ui/skins/default/button_square_togle_selected_underlay.png"
					uniqueguid="2B7C285A-BB2F-484B-AAB12DF4E4421357"/>
				<component_image_uniqueguid
					name="ui/skins/default/button_square_togle_selected_inactive.png"
					uniqueguid="D68CBAA2-EDA5-46F0-B69808121EF2D8DD"/>
				<component_image_uniqueguid
					name="ui/skins/default/button_square_togle_selected_pressed.png"
					uniqueguid="2617CB99-4EB6-4DB5-95803247A10211ED"/>
			</component_image_uniqueguids>
			<callbacks_with_context>
				<callback_with_context
					callback_id="ContextCommandLeftClick"
					context_object_id="CcoBattleTimeControl"
					context_function_id="SetSpeed(1)"/>
				<callback_with_context
					callback_id="ContextStateSetterConditional"
					context_object_id="CcoBattleTimeControl">
					<child_m_user_properties>
						<property
							name="event0"
							value="BattleTimeSpeedChanged"/>
						<property
							name="fallback_state"
							value="active"/>
						<property
							name="handle_button_states"
							value=""/>
						<property
							name="inactive"
							value="CanChangeTime == false"/>
						<property
							name="selected"
							value="CurrentSpeed == 1"/>
					</child_m_user_properties>
				</callback_with_context>
				<callback_with_context callback_id="CallbackAnimTrigger"/>
			</callbacks_with_context>
			<user_properties>
				<property
					name="disable_override"
					value="resizable"/>
				<property
					name="disable_override0"
					value="CallbackAnimTrigger"/>
				<property
					name="dynamic_image"
					value="0"/>
			</user_properties>
			<localised_texts>
				<localised_text
					tooltip_label="ComponentTooltip_ae78d033"
					tooltip_text="Play"/>
				<localised_text
					state="active"
					is_text_localised="false"/>
				<localised_text
					state="down"
					is_text_localised="false"/>
				<localised_text
					state="down_off"
					is_text_localised="false"/>
				<localised_text
					state="hover"
					is_text_localised="false"/>
				<localised_text
					state="inactive"
					is_text_localised="false"/>
				<localised_text
					state="selected"
					is_text_localised="false"/>
				<localised_text
					state="selected_down"
					is_text_localised="false"/>
				<localised_text
					state="selected_down_off"
					is_text_localised="false"/>
				<localised_text
					state="selected_hover"
					is_text_localised="false"/>
				<localised_text
					state="selected_inactive"
					is_text_localised="false"/>
			</localised_texts>
			<override_images>
				<element value="ui/skins/default/icon_speed_controls_button_play.png"/>
				<element value="ui/skins/default/button_square_togle_pressed.png"/>
				<element value="ui/skins/default/button_square_togle_selected_hover.png"/>
				<element value="ui/skins/default/button_square_togle_hover.png"/>
				<element value="ui/skins/default/button_square_togle_active.png"/>
				<element value="ui/skins/default/button_square_togle_inactive.png"/>
				<element value="ui/skins/default/button_square_togle_selected.png"/>
				<element value="ui/skins/default/button_square_togle_underlay.png"/>
				<element value="ui/skins/default/button_square_togle_selected_underlay.png"/>
				<element value="ui/skins/default/button_square_togle_selected_inactive.png"/>
				<element value="ui/skins/default/button_square_togle_selected_pressed.png"/>
				<element value=""/>
			</override_images>
        </button_hero_phase>
        <button_move_phase 
            this="34A720E2-1272-4654-94D8C98F2A71485D"
            id="button_move_phase"
            template_id="square_button_toggle_40"
			part_of_template="true"
			uniqueguid_in_template="2201BA48-5C83-4D09-9632B78D5B52ACCB"
			uniqueguid="34A720E2-1272-4654-94D8C98F2A71485D"
			dimensions="40.00,40.00"
			dock_point="Center Right"
			offset="-76.00,0.00"
			sound_category="UI_GBL_TMP_Round_Small_Button">
			<state_uniqueguids>
				<state_uniqueguid
					name="active"
					uniqueguid="4E7A65BF-AFB4-4D63-9D5E87145CC41D4D"/>
				<state_uniqueguid
					name="down"
					uniqueguid="AD2D681C-EA7E-4333-A684995201E55B61"/>
				<state_uniqueguid
					name="down_off"
					uniqueguid="430FC846-773B-4CE7-94DC270B2C4DCB86"/>
				<state_uniqueguid
					name="hover"
					uniqueguid="3B1624C7-BDB8-4C27-AFF140AA8EEC8AB9"/>
				<state_uniqueguid
					name="inactive"
					uniqueguid="07BCFC1C-C324-40D7-8E4AF6207E28F435"/>
				<state_uniqueguid
					name="selected"
					uniqueguid="7162627E-99B9-45D3-953AC04A02104662"/>
				<state_uniqueguid
					name="selected_down"
					uniqueguid="7555C34F-A306-49F4-A5F8912D37234966"/>
				<state_uniqueguid
					name="selected_down_off"
					uniqueguid="B9F9EA44-D87F-4099-B1C1DDF6339E0710"/>
				<state_uniqueguid
					name="selected_hover"
					uniqueguid="AF468B97-4E99-4A1B-9E3DEFB338A07AD1"/>
				<state_uniqueguid
					name="selected_inactive"
					uniqueguid="2099706B-4DB1-4AF3-A033E32E08E50119"/>
			</state_uniqueguids>
			<component_image_uniqueguids>
				<component_image_uniqueguid
					name="ui/skins/default/icon_speed_controls_button_play.png"
					uniqueguid="2597AC4C-2CC7-4290-99757027289F716B"/>
				<component_image_uniqueguid
					name="ui/skins/default/button_square_togle_pressed.png"
					uniqueguid="B2B13476-45A8-4BD4-9438CE1A8BD65678"/>
				<component_image_uniqueguid
					name="ui/skins/default/button_square_togle_selected_hover.png"
					uniqueguid="4B179BDF-446C-4865-B8B357BF3F19AF7E"/>
				<component_image_uniqueguid
					name="ui/skins/default/button_square_togle_hover.png"
					uniqueguid="450BF8F5-0377-4B2D-8D130017D751CE45"/>
				<component_image_uniqueguid
					name="ui/skins/default/button_square_togle_active.png"
					uniqueguid="04DF47F5-2311-4007-A02B823D4390A5E2"/>
				<component_image_uniqueguid
					name="ui/skins/default/button_square_togle_inactive.png"
					uniqueguid="2BEA714F-FE22-4418-BCA0E78F250E46CE"/>
				<component_image_uniqueguid
					name="ui/skins/default/button_square_togle_selected.png"
					uniqueguid="35AA89ED-9E9F-4192-9FD9C0ABDABE7596"/>
				<component_image_uniqueguid
					name="ui/skins/default/button_square_togle_underlay.png"
					uniqueguid="0A408CD2-857A-49C4-A55A79FEEDD18AB7"/>
				<component_image_uniqueguid
					name="ui/skins/default/button_square_togle_selected_underlay.png"
					uniqueguid="2B7C285A-BB2F-484B-AAB12DF4E4421357"/>
				<component_image_uniqueguid
					name="ui/skins/default/button_square_togle_selected_inactive.png"
					uniqueguid="D68CBAA2-EDA5-46F0-B69808121EF2D8DD"/>
				<component_image_uniqueguid
					name="ui/skins/default/button_square_togle_selected_pressed.png"
					uniqueguid="2617CB99-4EB6-4DB5-95803247A10211ED"/>
			</component_image_uniqueguids>
			<callbacks_with_context>
				<callback_with_context
					callback_id="ContextCommandLeftClick"
					context_object_id="CcoBattleTimeControl"
					context_function_id="SetSpeed(1)"/>
				<callback_with_context
					callback_id="ContextStateSetterConditional"
					context_object_id="CcoBattleTimeControl">
					<child_m_user_properties>
						<property
							name="event0"
							value="BattleTimeSpeedChanged"/>
						<property
							name="fallback_state"
							value="active"/>
						<property
							name="handle_button_states"
							value=""/>
						<property
							name="inactive"
							value="CanChangeTime == false"/>
						<property
							name="selected"
							value="CurrentSpeed == 1"/>
					</child_m_user_properties>
				</callback_with_context>
				<callback_with_context callback_id="CallbackAnimTrigger"/>
			</callbacks_with_context>
			<user_properties>
				<property
					name="disable_override"
					value="resizable"/>
				<property
					name="disable_override0"
					value="CallbackAnimTrigger"/>
				<property
					name="dynamic_image"
					value="0"/>
			</user_properties>
			<localised_texts>
				<localised_text
					tooltip_label="ComponentTooltip_ae78d033"
					tooltip_text="Play"/>
				<localised_text
					state="active"
					is_text_localised="false"/>
				<localised_text
					state="down"
					is_text_localised="false"/>
				<localised_text
					state="down_off"
					is_text_localised="false"/>
				<localised_text
					state="hover"
					is_text_localised="false"/>
				<localised_text
					state="inactive"
					is_text_localised="false"/>
				<localised_text
					state="selected"
					is_text_localised="false"/>
				<localised_text
					state="selected_down"
					is_text_localised="false"/>
				<localised_text
					state="selected_down_off"
					is_text_localised="false"/>
				<localised_text
					state="selected_hover"
					is_text_localised="false"/>
				<localised_text
					state="selected_inactive"
					is_text_localised="false"/>
			</localised_texts>
			<override_images>
				<element value="ui/skins/default/icon_speed_controls_button_play.png"/>
				<element value="ui/skins/default/button_square_togle_pressed.png"/>
				<element value="ui/skins/default/button_square_togle_selected_hover.png"/>
				<element value="ui/skins/default/button_square_togle_hover.png"/>
				<element value="ui/skins/default/button_square_togle_active.png"/>
				<element value="ui/skins/default/button_square_togle_inactive.png"/>
				<element value="ui/skins/default/button_square_togle_selected.png"/>
				<element value="ui/skins/default/button_square_togle_underlay.png"/>
				<element value="ui/skins/default/button_square_togle_selected_underlay.png"/>
				<element value="ui/skins/default/button_square_togle_selected_inactive.png"/>
				<element value="ui/skins/default/button_square_togle_selected_pressed.png"/>
				<element value=""/>
			</override_images>
        </button_move_phase>
        <button_shoot_phase 
            this="45A720E2-1272-4654-94D8C98F2A71485D"
            id="button_shoot_phase"
            template_id="square_button_toggle_40"
			part_of_template="true"
			uniqueguid_in_template="3301BA48-5C83-4D09-9632B78D5B52ACCB"
			uniqueguid="45A720E2-1272-4654-94D8C98F2A71485D"
			dimensions="40.00,40.00"
			dock_point="Center Right"
			offset="-76.00,0.00"
			sound_category="UI_GBL_TMP_Round_Small_Button">
			<state_uniqueguids>
				<state_uniqueguid
					name="active"
					uniqueguid="4E7A65BF-AFB4-4D63-9D5E87145CC41D4D"/>
				<state_uniqueguid
					name="down"
					uniqueguid="AD2D681C-EA7E-4333-A684995201E55B61"/>
				<state_uniqueguid
					name="down_off"
					uniqueguid="430FC846-773B-4CE7-94DC270B2C4DCB86"/>
				<state_uniqueguid
					name="hover"
					uniqueguid="3B1624C7-BDB8-4C27-AFF140AA8EEC8AB9"/>
				<state_uniqueguid
					name="inactive"
					uniqueguid="07BCFC1C-C324-40D7-8E4AF6207E28F435"/>
				<state_uniqueguid
					name="selected"
					uniqueguid="7162627E-99B9-45D3-953AC04A02104662"/>
				<state_uniqueguid
					name="selected_down"
					uniqueguid="7555C34F-A306-49F4-A5F8912D37234966"/>
				<state_uniqueguid
					name="selected_down_off"
					uniqueguid="B9F9EA44-D87F-4099-B1C1DDF6339E0710"/>
				<state_uniqueguid
					name="selected_hover"
					uniqueguid="AF468B97-4E99-4A1B-9E3DEFB338A07AD1"/>
				<state_uniqueguid
					name="selected_inactive"
					uniqueguid="2099706B-4DB1-4AF3-A033E32E08E50119"/>
			</state_uniqueguids>
			<component_image_uniqueguids>
				<component_image_uniqueguid
					name="ui/skins/default/icon_speed_controls_button_play.png"
					uniqueguid="2597AC4C-2CC7-4290-99757027289F716B"/>
				<component_image_uniqueguid
					name="ui/skins/default/button_square_togle_pressed.png"
					uniqueguid="B2B13476-45A8-4BD4-9438CE1A8BD65678"/>
				<component_image_uniqueguid
					name="ui/skins/default/button_square_togle_selected_hover.png"
					uniqueguid="4B179BDF-446C-4865-B8B357BF3F19AF7E"/>
				<component_image_uniqueguid
					name="ui/skins/default/button_square_togle_hover.png"
					uniqueguid="450BF8F5-0377-4B2D-8D130017D751CE45"/>
				<component_image_uniqueguid
					name="ui/skins/default/button_square_togle_active.png"
					uniqueguid="04DF47F5-2311-4007-A02B823D4390A5E2"/>
				<component_image_uniqueguid
					name="ui/skins/default/button_square_togle_inactive.png"
					uniqueguid="2BEA714F-FE22-4418-BCA0E78F250E46CE"/>
				<component_image_uniqueguid
					name="ui/skins/default/button_square_togle_selected.png"
					uniqueguid="35AA89ED-9E9F-4192-9FD9C0ABDABE7596"/>
				<component_image_uniqueguid
					name="ui/skins/default/button_square_togle_underlay.png"
					uniqueguid="0A408CD2-857A-49C4-A55A79FEEDD18AB7"/>
				<component_image_uniqueguid
					name="ui/skins/default/button_square_togle_selected_underlay.png"
					uniqueguid="2B7C285A-BB2F-484B-AAB12DF4E4421357"/>
				<component_image_uniqueguid
					name="ui/skins/default/button_square_togle_selected_inactive.png"
					uniqueguid="D68CBAA2-EDA5-46F0-B69808121EF2D8DD"/>
				<component_image_uniqueguid
					name="ui/skins/default/button_square_togle_selected_pressed.png"
					uniqueguid="2617CB99-4EB6-4DB5-95803247A10211ED"/>
			</component_image_uniqueguids>
			<callbacks_with_context>
				<callback_with_context
					callback_id="ContextCommandLeftClick"
					context_object_id="CcoBattleTimeControl"
					context_function_id="SetSpeed(1)"/>
				<callback_with_context
					callback_id="ContextStateSetterConditional"
					context_object_id="CcoBattleTimeControl">
					<child_m_user_properties>
						<property
							name="event0"
							value="BattleTimeSpeedChanged"/>
						<property
							name="fallback_state"
							value="active"/>
						<property
							name="handle_button_states"
							value=""/>
						<property
							name="inactive"
							value="CanChangeTime == false"/>
						<property
							name="selected"
							value="CurrentSpeed == 1"/>
					</child_m_user_properties>
				</callback_with_context>
				<callback_with_context callback_id="CallbackAnimTrigger"/>
			</callbacks_with_context>
			<user_properties>
				<property
					name="disable_override"
					value="resizable"/>
				<property
					name="disable_override0"
					value="CallbackAnimTrigger"/>
				<property
					name="dynamic_image"
					value="0"/>
			</user_properties>
			<localised_texts>
				<localised_text
					tooltip_label="ComponentTooltip_ae78d033"
					tooltip_text="Play"/>
				<localised_text
					state="active"
					is_text_localised="false"/>
				<localised_text
					state="down"
					is_text_localised="false"/>
				<localised_text
					state="down_off"
					is_text_localised="false"/>
				<localised_text
					state="hover"
					is_text_localised="false"/>
				<localised_text
					state="inactive"
					is_text_localised="false"/>
				<localised_text
					state="selected"
					is_text_localised="false"/>
				<localised_text
					state="selected_down"
					is_text_localised="false"/>
				<localised_text
					state="selected_down_off"
					is_text_localised="false"/>
				<localised_text
					state="selected_hover"
					is_text_localised="false"/>
				<localised_text
					state="selected_inactive"
					is_text_localised="false"/>
			</localised_texts>
			<override_images>
				<element value="ui/skins/default/icon_speed_controls_button_play.png"/>
				<element value="ui/skins/default/button_square_togle_pressed.png"/>
				<element value="ui/skins/default/button_square_togle_selected_hover.png"/>
				<element value="ui/skins/default/button_square_togle_hover.png"/>
				<element value="ui/skins/default/button_square_togle_active.png"/>
				<element value="ui/skins/default/button_square_togle_inactive.png"/>
				<element value="ui/skins/default/button_square_togle_selected.png"/>
				<element value="ui/skins/default/button_square_togle_underlay.png"/>
				<element value="ui/skins/default/button_square_togle_selected_underlay.png"/>
				<element value="ui/skins/default/button_square_togle_selected_inactive.png"/>
				<element value="ui/skins/default/button_square_togle_selected_pressed.png"/>
				<element value=""/>
			</override_images>
        </button_shoot_phase>
        <button_charge_phase 
            this="56A720E2-1272-4654-94D8C98F2A71485D"
            id="button_charge_phase"
            template_id="square_button_toggle_40"
			part_of_template="true"
			uniqueguid_in_template="4401BA48-5C83-4D09-9632B78D5B52ACCB"
			uniqueguid="56A720E2-1272-4654-94D8C98F2A71485D"
			dimensions="40.00,40.00"
			dock_point="Center Right"
			offset="-76.00,0.00"
			sound_category="UI_GBL_TMP_Round_Small_Button">
			<state_uniqueguids>
				<state_uniqueguid
					name="active"
					uniqueguid="4E7A65BF-AFB4-4D63-9D5E87145CC41D4D"/>
				<state_uniqueguid
					name="down"
					uniqueguid="AD2D681C-EA7E-4333-A684995201E55B61"/>
				<state_uniqueguid
					name="down_off"
					uniqueguid="430FC846-773B-4CE7-94DC270B2C4DCB86"/>
				<state_uniqueguid
					name="hover"
					uniqueguid="3B1624C7-BDB8-4C27-AFF140AA8EEC8AB9"/>
				<state_uniqueguid
					name="inactive"
					uniqueguid="07BCFC1C-C324-40D7-8E4AF6207E28F435"/>
				<state_uniqueguid
					name="selected"
					uniqueguid="7162627E-99B9-45D3-953AC04A02104662"/>
				<state_uniqueguid
					name="selected_down"
					uniqueguid="7555C34F-A306-49F4-A5F8912D37234966"/>
				<state_uniqueguid
					name="selected_down_off"
					uniqueguid="B9F9EA44-D87F-4099-B1C1DDF6339E0710"/>
				<state_uniqueguid
					name="selected_hover"
					uniqueguid="AF468B97-4E99-4A1B-9E3DEFB338A07AD1"/>
				<state_uniqueguid
					name="selected_inactive"
					uniqueguid="2099706B-4DB1-4AF3-A033E32E08E50119"/>
			</state_uniqueguids>
			<component_image_uniqueguids>
				<component_image_uniqueguid
					name="ui/skins/default/icon_speed_controls_button_play.png"
					uniqueguid="2597AC4C-2CC7-4290-99757027289F716B"/>
				<component_image_uniqueguid
					name="ui/skins/default/button_square_togle_pressed.png"
					uniqueguid="B2B13476-45A8-4BD4-9438CE1A8BD65678"/>
				<component_image_uniqueguid
					name="ui/skins/default/button_square_togle_selected_hover.png"
					uniqueguid="4B179BDF-446C-4865-B8B357BF3F19AF7E"/>
				<component_image_uniqueguid
					name="ui/skins/default/button_square_togle_hover.png"
					uniqueguid="450BF8F5-0377-4B2D-8D130017D751CE45"/>
				<component_image_uniqueguid
					name="ui/skins/default/button_square_togle_active.png"
					uniqueguid="04DF47F5-2311-4007-A02B823D4390A5E2"/>
				<component_image_uniqueguid
					name="ui/skins/default/button_square_togle_inactive.png"
					uniqueguid="2BEA714F-FE22-4418-BCA0E78F250E46CE"/>
				<component_image_uniqueguid
					name="ui/skins/default/button_square_togle_selected.png"
					uniqueguid="35AA89ED-9E9F-4192-9FD9C0ABDABE7596"/>
				<component_image_uniqueguid
					name="ui/skins/default/button_square_togle_underlay.png"
					uniqueguid="0A408CD2-857A-49C4-A55A79FEEDD18AB7"/>
				<component_image_uniqueguid
					name="ui/skins/default/button_square_togle_selected_underlay.png"
					uniqueguid="2B7C285A-BB2F-484B-AAB12DF4E4421357"/>
				<component_image_uniqueguid
					name="ui/skins/default/button_square_togle_selected_inactive.png"
					uniqueguid="D68CBAA2-EDA5-46F0-B69808121EF2D8DD"/>
				<component_image_uniqueguid
					name="ui/skins/default/button_square_togle_selected_pressed.png"
					uniqueguid="2617CB99-4EB6-4DB5-95803247A10211ED"/>
			</component_image_uniqueguids>
			<callbacks_with_context>
				<callback_with_context
					callback_id="ContextCommandLeftClick"
					context_object_id="CcoBattleTimeControl"
					context_function_id="SetSpeed(1)"/>
				<callback_with_context
					callback_id="ContextStateSetterConditional"
					context_object_id="CcoBattleTimeControl">
					<child_m_user_properties>
						<property
							name="event0"
							value="BattleTimeSpeedChanged"/>
						<property
							name="fallback_state"
							value="active"/>
						<property
							name="handle_button_states"
							value=""/>
						<property
							name="inactive"
							value="CanChangeTime == false"/>
						<property
							name="selected"
							value="CurrentSpeed == 1"/>
					</child_m_user_properties>
				</callback_with_context>
				<callback_with_context callback_id="CallbackAnimTrigger"/>
			</callbacks_with_context>
			<user_properties>
				<property
					name="disable_override"
					value="resizable"/>
				<property
					name="disable_override0"
					value="CallbackAnimTrigger"/>
				<property
					name="dynamic_image"
					value="0"/>
			</user_properties>
			<localised_texts>
				<localised_text
					tooltip_label="ComponentTooltip_ae78d033"
					tooltip_text="Play"/>
				<localised_text
					state="active"
					is_text_localised="false"/>
				<localised_text
					state="down"
					is_text_localised="false"/>
				<localised_text
					state="down_off"
					is_text_localised="false"/>
				<localised_text
					state="hover"
					is_text_localised="false"/>
				<localised_text
					state="inactive"
					is_text_localised="false"/>
				<localised_text
					state="selected"
					is_text_localised="false"/>
				<localised_text
					state="selected_down"
					is_text_localised="false"/>
				<localised_text
					state="selected_down_off"
					is_text_localised="false"/>
				<localised_text
					state="selected_hover"
					is_text_localised="false"/>
				<localised_text
					state="selected_inactive"
					is_text_localised="false"/>
			</localised_texts>
			<override_images>
				<element value="ui/skins/default/icon_speed_controls_button_play.png"/>
				<element value="ui/skins/default/button_square_togle_pressed.png"/>
				<element value="ui/skins/default/button_square_togle_selected_hover.png"/>
				<element value="ui/skins/default/button_square_togle_hover.png"/>
				<element value="ui/skins/default/button_square_togle_active.png"/>
				<element value="ui/skins/default/button_square_togle_inactive.png"/>
				<element value="ui/skins/default/button_square_togle_selected.png"/>
				<element value="ui/skins/default/button_square_togle_underlay.png"/>
				<element value="ui/skins/default/button_square_togle_selected_underlay.png"/>
				<element value="ui/skins/default/button_square_togle_selected_inactive.png"/>
				<element value="ui/skins/default/button_square_togle_selected_pressed.png"/>
				<element value=""/>
			</override_images>
        </button_charge_phase>
        <button_fight_phase 
            this="67A720E2-1272-4654-94D8C98F2A71485D"
            id="button_fight_phase"
            template_id="square_button_toggle_40"
			part_of_template="true"
			uniqueguid_in_template="5501BA48-5C83-4D09-9632B78D5B52ACCB"
			uniqueguid="67A720E2-1272-4654-94D8C98F2A71485D"
			dimensions="40.00,40.00"
			dock_point="Center Right"
			offset="-76.00,0.00"
			sound_category="UI_GBL_TMP_Round_Small_Button">
			<state_uniqueguids>
				<state_uniqueguid
					name="active"
					uniqueguid="4E7A65BF-AFB4-4D63-9D5E87145CC41D4D"/>
				<state_uniqueguid
					name="down"
					uniqueguid="AD2D681C-EA7E-4333-A684995201E55B61"/>
				<state_uniqueguid
					name="down_off"
					uniqueguid="430FC846-773B-4CE7-94DC270B2C4DCB86"/>
				<state_uniqueguid
					name="hover"
					uniqueguid="3B1624C7-BDB8-4C27-AFF140AA8EEC8AB9"/>
				<state_uniqueguid
					name="inactive"
					uniqueguid="07BCFC1C-C324-40D7-8E4AF6207E28F435"/>
				<state_uniqueguid
					name="selected"
					uniqueguid="7162627E-99B9-45D3-953AC04A02104662"/>
				<state_uniqueguid
					name="selected_down"
					uniqueguid="7555C34F-A306-49F4-A5F8912D37234966"/>
				<state_uniqueguid
					name="selected_down_off"
					uniqueguid="B9F9EA44-D87F-4099-B1C1DDF6339E0710"/>
				<state_uniqueguid
					name="selected_hover"
					uniqueguid="AF468B97-4E99-4A1B-9E3DEFB338A07AD1"/>
				<state_uniqueguid
					name="selected_inactive"
					uniqueguid="2099706B-4DB1-4AF3-A033E32E08E50119"/>
			</state_uniqueguids>
			<component_image_uniqueguids>
				<component_image_uniqueguid
					name="ui/skins/default/icon_speed_controls_button_play.png"
					uniqueguid="2597AC4C-2CC7-4290-99757027289F716B"/>
				<component_image_uniqueguid
					name="ui/skins/default/button_square_togle_pressed.png"
					uniqueguid="B2B13476-45A8-4BD4-9438CE1A8BD65678"/>
				<component_image_uniqueguid
					name="ui/skins/default/button_square_togle_selected_hover.png"
					uniqueguid="4B179BDF-446C-4865-B8B357BF3F19AF7E"/>
				<component_image_uniqueguid
					name="ui/skins/default/button_square_togle_hover.png"
					uniqueguid="450BF8F5-0377-4B2D-8D130017D751CE45"/>
				<component_image_uniqueguid
					name="ui/skins/default/button_square_togle_active.png"
					uniqueguid="04DF47F5-2311-4007-A02B823D4390A5E2"/>
				<component_image_uniqueguid
					name="ui/skins/default/button_square_togle_inactive.png"
					uniqueguid="2BEA714F-FE22-4418-BCA0E78F250E46CE"/>
				<component_image_uniqueguid
					name="ui/skins/default/button_square_togle_selected.png"
					uniqueguid="35AA89ED-9E9F-4192-9FD9C0ABDABE7596"/>
				<component_image_uniqueguid
					name="ui/skins/default/button_square_togle_underlay.png"
					uniqueguid="0A408CD2-857A-49C4-A55A79FEEDD18AB7"/>
				<component_image_uniqueguid
					name="ui/skins/default/button_square_togle_selected_underlay.png"
					uniqueguid="2B7C285A-BB2F-484B-AAB12DF4E4421357"/>
				<component_image_uniqueguid
					name="ui/skins/default/button_square_togle_selected_inactive.png"
					uniqueguid="D68CBAA2-EDA5-46F0-B69808121EF2D8DD"/>
				<component_image_uniqueguid
					name="ui/skins/default/button_square_togle_selected_pressed.png"
					uniqueguid="2617CB99-4EB6-4DB5-95803247A10211ED"/>
			</component_image_uniqueguids>
			<callbacks_with_context>
				<callback_with_context
					callback_id="ContextCommandLeftClick"
					context_object_id="CcoBattleTimeControl"
					context_function_id="SetSpeed(1)"/>
				<callback_with_context
					callback_id="ContextStateSetterConditional"
					context_object_id="CcoBattleTimeControl">
					<child_m_user_properties>
						<property
							name="event0"
							value="BattleTimeSpeedChanged"/>
						<property
							name="fallback_state"
							value="active"/>
						<property
							name="handle_button_states"
							value=""/>
						<property
							name="inactive"
							value="CanChangeTime == false"/>
						<property
							name="selected"
							value="CurrentSpeed == 1"/>
					</child_m_user_properties>
				</callback_with_context>
				<callback_with_context callback_id="CallbackAnimTrigger"/>
			</callbacks_with_context>
			<user_properties>
				<property
					name="disable_override"
					value="resizable"/>
				<property
					name="disable_override0"
					value="CallbackAnimTrigger"/>
				<property
					name="dynamic_image"
					value="0"/>
			</user_properties>
			<localised_texts>
				<localised_text
					tooltip_label="ComponentTooltip_ae78d033"
					tooltip_text="Play"/>
				<localised_text
					state="active"
					is_text_localised="false"/>
				<localised_text
					state="down"
					is_text_localised="false"/>
				<localised_text
					state="down_off"
					is_text_localised="false"/>
				<localised_text
					state="hover"
					is_text_localised="false"/>
				<localised_text
					state="inactive"
					is_text_localised="false"/>
				<localised_text
					state="selected"
					is_text_localised="false"/>
				<localised_text
					state="selected_down"
					is_text_localised="false"/>
				<localised_text
					state="selected_down_off"
					is_text_localised="false"/>
				<localised_text
					state="selected_hover"
					is_text_localised="false"/>
				<localised_text
					state="selected_inactive"
					is_text_localised="false"/>
			</localised_texts>
			<override_images>
				<element value="ui/skins/default/icon_speed_controls_button_play.png"/>
				<element value="ui/skins/default/button_square_togle_pressed.png"/>
				<element value="ui/skins/default/button_square_togle_selected_hover.png"/>
				<element value="ui/skins/default/button_square_togle_hover.png"/>
				<element value="ui/skins/default/button_square_togle_active.png"/>
				<element value="ui/skins/default/button_square_togle_inactive.png"/>
				<element value="ui/skins/default/button_square_togle_selected.png"/>
				<element value="ui/skins/default/button_square_togle_underlay.png"/>
				<element value="ui/skins/default/button_square_togle_selected_underlay.png"/>
				<element value="ui/skins/default/button_square_togle_selected_inactive.png"/>
				<element value="ui/skins/default/button_square_togle_selected_pressed.png"/>
				<element value=""/>
			</override_images>
        </button_fight_phase>
        <next_phase_button 
            this="78A720E2-1272-4654-94D8C98F2A71485D"
            id="next_phase_button"
            template_id="round_medium_button"
			part_of_template="true"
			uniqueguid_in_template="6608AA99-2BAB-4DB6-AC47ACC0CEBD26BE"
			uniqueguid="78A720E2-1272-4654-94D8C98F2A71485D"
			dimensions="56.00,56.00"
			dock_point="Top Right"
			offset="-2.00,4.00"
			priority="2"
			sound_category="UI_GBL_HUD_Tactical_Map_Open">
			<state_uniqueguids>
				<state_uniqueguid
					name="active"
					uniqueguid="68B5DC2B-DA18-47B6-90A47D53211E67E8"/>
				<state_uniqueguid
					name="down"
					uniqueguid="3DCFB99E-E8E3-4911-AA660F4627988332"/>
				<state_uniqueguid
					name="down_off"
					uniqueguid="53A646B7-1694-42F7-BA6B3E4DB30090C3"/>
				<state_uniqueguid
					name="hover"
					uniqueguid="DF640030-5CBA-4F6E-B9873DCFAEDE6E84"/>
				<state_uniqueguid
					name="inactive"
					uniqueguid="CE9352D6-7C26-4209-8B7A3EFBF2FAAD18"/>
			</state_uniqueguids>
			<component_image_uniqueguids>
				<component_image_uniqueguid
					name="ui/skins/default/icon_medium_tactical_map.png"
					uniqueguid="5FFAF4BD-D9C6-45C6-985A71AC2A2057CE"/>
				<component_image_uniqueguid
					name="ui/skins/default/button_round_medium_pressed.png"
					uniqueguid="7B7E4491-EF8D-45ED-AB9667F717B3C8F3"/>
				<component_image_uniqueguid
					name="ui/skins/default/button_round_medium_hover.png"
					uniqueguid="F11021BD-A085-4FFF-8EE6372D168DA028"/>
				<component_image_uniqueguid
					name="ui/skins/default/button_round_medium_active.png"
					uniqueguid="BCD321EF-31D0-4967-B95C7A0E36EA5A61"/>
				<component_image_uniqueguid
					name="ui/skins/default/button_round_medium_inactive.png"
					uniqueguid="444A7E36-D0D1-4409-AAF7EE7D6F49B730"/>
				<component_image_uniqueguid
					name="ui/skins/default/button_round_medium_underlay.png"
					uniqueguid="C9F34759-2379-48C3-A39B768727403754"/>
			</component_image_uniqueguids>
			<callbacks_with_context>
				<callback_with_context callback_id="BattleButtonTacticalToggle"/>
				<callback_with_context callback_id="StatePropagatorCallback">
					<child_m_user_properties>
						<property
							name="use_transitions"
							value=""/>
					</child_m_user_properties>
				</callback_with_context>
				<callback_with_context callback_id="CallbackAnimTrigger"/>
			</callbacks_with_context>
			<user_properties>
				<property
					name="disable_override"
					value="resizable"/>
				<property
					name="disable_override0"
					value="CallbackAnimTrigger"/>
				<property
					name="dynamic_image"
					value="0"/>
				<property
					name="override_sound"
					value=""/>
			</user_properties>
			<localised_texts>
				<localised_text
					tooltip_label="button_tactical_map_Tooltip_130058"
					tooltip_text="Toggle Tactical Map"/>
				<localised_text
					state="active"
					is_text_localised="false"/>
				<localised_text
					state="down"
					is_text_localised="false"/>
				<localised_text
					state="down_off"
					is_text_localised="false"/>
				<localised_text
					state="hover"
					is_text_localised="false"/>
				<localised_text
					state="inactive"
					is_text_localised="false"/>
			</localised_texts>
			<override_images>
				<element value="ui/skins/default/icon_medium_tactical_map.png"/>
				<element value="ui/skins/default/button_round_medium_pressed.png"/>
				<element value="ui/skins/default/button_round_medium_hover.png"/>
				<element value="ui/skins/default/button_round_medium_active.png"/>
				<element value="ui/skins/default/button_round_medium_inactive.png"/>
				<element value="ui/skins/default/button_round_medium_underlay.png"/>
				<element value=""/>
			</override_images>
        </next_phase_button>
		<root
			this="34001338-B13C-4056-8A97BE79D1094FA9"
			id="root"
			uniqueguid_in_template="77001338-B13C-4056-8A97BE79D1094FA9"
			tooltipslocalised="true"
			uniqueguid="34001338-B13C-4056-8A97BE79D1094FA9"
			currentstate="3400861C-8BE6-4E0C-99A2A5B20BDCBDD7"
			defaultstate="3400861C-8BE6-4E0C-99A2A5B20BDCBDD7">
			<componentimages>
				<component_image
					this="34008DF4-C436-4C9F-941E094A9021EF16"
					uniqueguid="34008DF4-C436-4C9F-941E094A9021EF16"/>
			</componentimages>
			<states>
				<newstate
					this="3400861C-8BE6-4E0C-99A2A5B20BDCBDD7"
					name="NewState"
					width="1600"
					height="900"
					interactive="true"
					uniqueguid="3400861C-8BE6-4E0C-99A2A5B20BDCBDD7">
					<imagemetrics>
						<image
							this="34009286-6575-439F-AFB94E5F9B333DB4"
							uniqueguid="34009286-6575-439F-AFB94E5F9B333DB4"
							componentimage="34008DF4-C436-4C9F-941E094A9021EF16"
							width="1920"
							height="1080"
							colour="#F0F0F0FF"/>
					</imagemetrics>
				</newstate>
			</states>
		</root>
	</components>
</layout>
